Combinational Circuits/DEMUX/demux_1to8.v
module demux1to4(
    input din,
    input [1:0] sel,
    output [3:0] out
);
    assign out[0] = (~sel[1] & ~sel[0]) & din;
    assign out[1] = (~sel[1] &  sel[0]) & din;
    assign out[2] = ( sel[1] & ~sel[0]) & din;
    assign out[3] = ( sel[1] &  sel[0]) & din;
endmodule

module demux1to8(
    input din,
    input [2:0] sel,
    output [7:0] out
);
    wire upper, lower;
    wire [3:0] out_upper, out_lower;

    // First demux divides din into two halves based on sel[2]
    assign lower = (~sel[2]) & din;
    assign upper = ( sel[2]) & din;

    // Lower 4 outputs
    demux1to4 d0 (
        .din(lower),
        .sel(sel[1:0]),
        .out(out[3:0])
    );

        demux1to4 d1 (
        .din(upper),
        .sel(sel[1:0]),
        .out(out[7:4])
    );
endmodule

Combinational Circuits/DEMUX/demux1to8_tb.v
module demux1to8_tb;
    reg din;
    reg [2:0] sel;
    wire [7:0] out;

    // Instantiate the DUT (Device Under Test)
    demux1to8 uut (
        .din(din),
        .sel(sel),
        .out(out)
    );

    initial begin
        $dumpfile("demux1to8_out.vcd");
        $dumpvars(0, demux1to8_tb);
        $monitor("Time=%0t | din=%b sel=%b | out=%b", $time, din, sel, out);

        din = 1;

        // Test all selector values
        sel = 3'b000; #10;
        sel = 3'b001; #10;
        sel = 3'b010; #10;
        sel = 3'b011; #10;
        sel = 3'b100; #10;
        sel = 3'b101; #10;
        sel = 3'b110; #10;
        sel = 3'b111; #10;

        // Test with din = 0
        din = 0; sel = 3'b000; #10;
        sel = 3'b101; #10;

        $finish;
    end
endmodule

Combinational Circuits/DEMUX/demux1to8_out.vcd
$date
	Wed Jul 23 22:17:05 2025
$end
$version
	Icarus Verilog
$end
$timescale
	1s
$end
$scope module demux1to8_tb $end
$var wire 8 ! out [7:0] $end
$var reg 1 " din $end
$var reg 3 # sel [2:0] $end
$scope module uut $end
$var wire 1 $ din $end
$var wire 1 % lower $end
$var wire 8 & out [7:0] $end
$var wire 3 ' sel [2:0] $end
$var wire 1 ( upper $end
$scope module d0 $end
$var wire 1 % din $end
$var wire 4 ) out [3:0] $end
$var wire 2 * sel [1:0] $end
$upscope $end
$scope module d1 $end
$var wire 1 ( din $end
$var wire 4 + out [3:0] $end
$var wire 2 , sel [1:0] $end
$upscope $end
$upscope $end
$upscope $end
$enddefinitions $end
#0
$dumpvars
b0 ,
b0 +
b0 *
b1 )
0(
b0 '
b1 &
1%
1$
b0 #
1"
b1 !
$end
#10
b10 !
b10 &
b10 )
b1 *
b1 ,
b1 #
b1 '
#20
b100 !
b100 &
b100 )
b10 *
b10 ,
b10 #
b10 '
#30
b1000 !
b1000 &
b1000 )
b11 *
b11 ,
b11 #
b11 '
#40
b1 +
b10000 !
b10000 &
b0 )
0%
1(
b0 *
b0 ,
b100 #
b100 '
#50
b100000 !
b100000 &
b10 +
b1 *
b1 ,
b101 #
b101 '
#60
b1000000 !
b1000000 &
b100 +
b10 *
b10 ,
b110 #
b110 '
#70
b10000000 !
b10000000 &
b1000 +
b11 *
b11 ,
b111 #
b111 '
#80
b0 !
b0 &
b0 +
b0 *
b0 ,
0(
b0 #
b0 '
0"
0$
#90
b1 *
b1 ,
b101 #
b101 '
