Combinational Circuits/DEMUX/demux.v
module demux(
    input din,
    input [1:0] sel,
    output reg [3:0] out
);
    always @(*) begin
        out = 4'b0000;
        case(sel)
            2'b00: out[0] = din;
            2'b01: out[1] = din;
            2'b10: out[2] = din;
            2'b11: out[3] = din;
        endcase
    end
endmodule

Combinational Circuits/DEMUX/demux_tb.v
module demux_tb;
    reg din;
    reg [1:0] sel;
    wire [3:0] out;

    demux uut (.din(din), .sel(sel), .out(out));

    initial begin
        $dumpfile("demux_out.vcd");
        $dumpvars(0, demux_tb);
        $monitor("Time=%0t | din=%b sel=%b | out=%b", $time, din, sel, out);

        din = 1;
        sel = 2'b00; #10;
        sel = 2'b01; #10;
        sel = 2'b10; #10;
        sel = 2'b11; #10;
        
        din = 0;
        sel = 2'b00; #10;
        sel = 2'b01; #10;
        sel = 2'b10; #10;
        sel = 2'b11; #10;

        $finish;
    end
endmodule

Combinational Circuits/DEMUX/demux_out.vcd
$date
	Fri Jul 18 23:33:15 2025
$end
$version
	Icarus Verilog
$end
$timescale
	1s
$end
$scope module demux_tb $end
$var wire 4 ! out [3:0] $end
$var reg 1 " din $end
$var reg 2 # sel [1:0] $end
$scope module uut $end
$var wire 1 $ din $end
$var wire 2 % sel [1:0] $end
$var reg 4 & out [3:0] $end
$upscope $end
$upscope $end
$enddefinitions $end
#0
$dumpvars
b1 &
b0 %
1$
b0 #
1"
b1 !
$end
#10
b10 &
b10 !
b1 #
b1 %
#20
b100 &
b100 !
b10 #
b10 %
#30
b1000 &
b1000 !
b11 #
b11 %
#40
b0 &
b0 !
b0 #
b0 %
0"
0$
#50
b0 &
b1 #
b1 %
#60
b0 &
b10 #
b10 %
#70
b0 &
b11 #
b11 %
