Combinational Circuits/Full Subtractor/full_subtractor_dataflow.v
module full_subtractor_dataflow(
    input A, B, Bin,
    output Difference, Borrow
);
assign Difference = A ^ B ^ Bin;
assign Borrow = (~A & B) | (B & Bin) | (~A & Bin);
endmodule

Combinational Circuits/Full Subtractor/full_subtractor_tb.v
`timescale 1ns / 1ps

module full_subtractor_tb;
    
    reg A, B, Bin;
    
    wire Difference, Borrow;
    
    
    full_subtractor_dataflow uut (
        .A(A), 
        .B(B), 
        .Bin(Bin), 
        .Difference(Difference), 
        .Borrow(Borrow)
    );

    initial begin
        $dumpfile("full_subtractor.vcd");
        $dumpvars(0, full_subtractor_tb);
        
        // Test all input combinations
        A = 0; B = 0; Bin = 0; #10;
        A = 0; B = 0; Bin = 1; #10;
        A = 0; B = 1; Bin = 0; #10;
        A = 0; B = 1; Bin = 1; #10;
        A = 1; B = 0; Bin = 0; #10;
        A = 1; B = 0; Bin = 1; #10;
        A = 1; B = 1; Bin = 0; #10;
        A = 1; B = 1; Bin = 1; #10;
        
        $finish;
    end
     
     initial begin
        $monitor("Time=%0t | A=%b B=%b Bin=%b | Difference=%b Borrow=%b", $time, A, B, Bin, Difference, Borrow);
    end

endmodule

Combinational Circuits/Full Subtractor/full_subtractor.vcd
$date
	Thu Jul 17 00:42:56 2025
$end
$version
	Icarus Verilog
$end
$timescale
	1ps
$end
$scope module full_subtractor_tb $end
$var wire 1 ! Borrow $end
$var wire 1 " Difference $end
$var reg 1 # A $end
$var reg 1 $ B $end
$var reg 1 % Bin $end
$scope module uut $end
$var wire 1 & A $end
$var wire 1 ' B $end
$var wire 1 ( Bin $end
$var wire 1 ! Borrow $end
$var wire 1 " Difference $end
$upscope $end
$upscope $end
$enddefinitions $end
#0
$dumpvars
0(
0'
0&
0%
0$
0#
0"
0!
$end
#10000
1!
1"
1%
1(
#20000
0%
0(
1$
1'
#30000
0"
1%
1(
#40000
0!
1"
0%
0(
0$
0'
1#
1&
#50000
0"
1%
1(
#60000
0%
0(
1$
1'
#70000
1!
1"
1%
1(
