Combinational Circuits/Decoder/decoder3to8.v

module decoder3to8 (
    input [2:0] in,
    input en,
    output reg [7:0] out
);

always @(*) begin
    if (en)
        case (in)
            3'b000: out = 8'b00000001;
            3'b001: out = 8'b00000010;
            3'b010: out = 8'b00000100;
            3'b011: out = 8'b00001000;
            3'b100: out = 8'b00010000;
            3'b101: out = 8'b00100000;
            3'b110: out = 8'b01000000;
            3'b111: out = 8'b10000000;
        endcase
    else
        out = 8'b00000000;
end

endmodule

Combinational Circuits/Decoder/decoder3to8_tb.v
`timescale 1ns/1ps
module decoder3to8_tb;

reg [2:0] in;
reg en;
wire [7:0] out;

// Instantiate the decoder
decoder3to8 uut (
    .in(in),
    .en(en),
    .out(out)
);

initial begin
    $dumpfile("decoder3to8_out.vcd");
    $dumpvars(0, decoder3to8_tb);

    // Enable = 1, test all inputs
    en = 1;
    in = 3'b000; #10;
    in = 3'b001; #10;
    in = 3'b010; #10;
    in = 3'b011; #10;
    in = 3'b100; #10;
    in = 3'b101; #10;
    in = 3'b110; #10;
    in = 3'b111; #10;

    // Enable = 0, test one input
    en = 0;
    in = 3'b101; #10;

    $finish;
end

endmodule

Combinational Circuits/Decoder/decoder3to8_out.vcd
$date
	Mon Jul 28 14:16:09 2025
$end
$version
	Icarus Verilog
$end
$timescale
	1ps
$end
$scope module decoder3to8_tb $end
$var wire 8 ! out [7:0] $end
$var reg 1 " en $end
$var reg 3 # in [2:0] $end
$scope module uut $end
$var wire 1 $ en $end
$var wire 3 % in [2:0] $end
$var reg 8 & out [7:0] $end
$upscope $end
$upscope $end
$enddefinitions $end
#0
$dumpvars
b1 &
b0 %
1$
b0 #
1"
b1 !
$end
#10000
b10 &
b10 !
b1 #
b1 %
#20000
b100 &
b100 !
b10 #
b10 %
#30000
b1000 &
b1000 !
b11 #
b11 %
#40000
b10000 &
b10000 !
b100 #
b100 %
#50000
b100000 &
b100000 !
b101 #
b101 %
#60000
b1000000 &
b1000000 !
b110 #
b110 %
#70000
b10000000 &
b10000000 !
b111 #
b111 %
#80000
b0 &
b0 !
b101 #
b101 %
0"
0$
