Combinational Circuits/MUX/8:1 MUX/mux8to1.v
module mux8to1(
    input [7:0] in,       // 8 data inputs
    input [2:0] sel,      // 3-bit select line
    output out            // Output
);
    assign out = (sel == 3'b000) ? in[0] :
                 (sel == 3'b001) ? in[1] :
                 (sel == 3'b010) ? in[2] :
                 (sel == 3'b011) ? in[3] :
                 (sel == 3'b100) ? in[4] :
                 (sel == 3'b101) ? in[5] :
                 (sel == 3'b110) ? in[6] :
                 in[7];
endmodule

Combinational Circuits/MUX/8:1 MUX/mux8to1_tb.v
`timescale 1ns/1ps

module mux8to1_tb;
    reg [7:0] in;
    reg [2:0] sel;
    wire out;

    // Instantiate the MUX
    mux8to1 uut (
        .in(in),
        .sel(sel),
        .out(out)
    );

    initial begin
        $dumpfile("mux8to1_out.vcd");    
        $dumpvars(0, mux8to1_tb);       

        // Monitor signal changes
        $monitor("Time=%0t | in=%b | sel=%b | out=%b", $time, in, sel, out);

        // Test case 1
        in = 8'b10101010;
        sel = 3'b000; #10;
        sel = 3'b001; #10;
        sel = 3'b010; #10;
        sel = 3'b011; #10;
        sel = 3'b100; #10;
        sel = 3'b101; #10;
        sel = 3'b110; #10;
        sel = 3'b111; #10;

        // Test case 2
        in = 8'b11001100;
        sel = 3'b000; #10;
        sel = 3'b100; #10;
        sel = 3'b111; #10;

        $finish;
    end
endmodule

Combinational Circuits/MUX/8:1 MUX/mux8to1_out.vcd
$date
	Fri Jul 18 11:42:41 2025
$end
$version
	Icarus Verilog
$end
$timescale
	1ps
$end
$scope module mux8to1_tb $end
$var wire 1 ! out $end
$var reg 8 " in [7:0] $end
$var reg 3 # sel [2:0] $end
$scope module uut $end
$var wire 8 $ in [7:0] $end
$var wire 1 ! out $end
$var wire 3 % sel [2:0] $end
$upscope $end
$upscope $end
$enddefinitions $end
#0
$dumpvars
b0 %
b10101010 $
b0 #
b10101010 "
0!
$end
#10000
1!
b1 #
b1 %
#20000
0!
b10 #
b10 %
#30000
1!
b11 #
b11 %
#40000
0!
b100 #
b100 %
#50000
1!
b101 #
b101 %
#60000
0!
b110 #
b110 %
#70000
1!
b111 #
b111 %
#80000
0!
b0 #
b0 %
b11001100 "
b11001100 $
#90000
0!
b100 #
b100 %
#100000
1!
b111 #
b111 %
