Sequential Circuits/Counters/Synchronous Counters/sync_up_counter.v
module sync_up_counter (
    input clk, reset,
    output reg [3:0] q
);

  
    always @(posedge clk or posedge reset) begin
        if (reset)
            q <= 4'b0000;   // start at 0
        else
            q <= q + 1;     // increment by 1 each clock
    end

endmodule

Sequential Circuits/Counters/Synchronous Counters/sync_up_counter_tb.v
`timescale 1ns/1ps
module sync_up_counter_tb;

    reg clk, reset;
    wire [3:0] q;

    // Instantiate the counter
    sync_up_counter uut (
        .clk(clk),
        .reset(reset),
        .q(q)
    );

    // Clock generation: 10ns period
    always #5 clk = ~clk;

    initial begin
        // VCD dump for GTKWave
        $dumpfile("sync_up_counter_out.vcd");
        $dumpvars(0, sync_up_counter_tb);

        // Initialize signals
        clk = 0;
        reset = 1;   // assert reset
        #12 reset = 0;  // release reset after 12ns

        // Run simulation long enough to see rollover
        #200 $finish;
    end

endmodule

Sequential Circuits/Counters/Synchronous Counters/sync_up_counter_out.vcd
$date
	Fri Oct 03 21:49:58 2025
$end
$version
	Icarus Verilog
$end
$timescale
	1ps
$end
$scope module sync_up_counter_tb $end
$var wire 4 ! q [3:0] $end
$var reg 1 " clk $end
$var reg 1 # reset $end
$scope module uut $end
$var wire 1 $ clk $end
$var wire 1 % reset $end
$var reg 4 & q [3:0] $end
$upscope $end
$upscope $end
$enddefinitions $end
#0
$dumpvars
b0 &
1%
0$
1#
0"
b0 !
$end
#5000
1"
1$
#10000
0"
0$
#12000
0#
0%
#15000
b1 &
b1 !
1"
1$
#20000
0"
0$
#25000
b10 &
b10 !
1"
1$
#30000
0"
0$
#35000
b11 &
b11 !
1"
1$
#40000
0"
0$
#45000
b100 &
b100 !
1"
1$
#50000
0"
0$
#55000
b101 &
b101 !
1"
1$
#60000
0"
0$
#65000
b110 &
b110 !
1"
1$
#70000
0"
0$
#75000
b111 &
b111 !
1"
1$
#80000
0"
0$
#85000
b1000 &
b1000 !
1"
1$
#90000
0"
0$
#95000
b1001 &
b1001 !
1"
1$
#100000
0"
0$
#105000
b1010 &
b1010 !
1"
1$
#110000
0"
0$
#115000
b1011 &
b1011 !
1"
1$
#120000
0"
0$
#125000
b1100 &
b1100 !
1"
1$
#130000
0"
0$
#135000
b1101 &
b1101 !
1"
1$
#140000
0"
0$
#145000
b1110 &
b1110 !
1"
1$
#150000
0"
0$
#155000
b1111 &
b1111 !
1"
1$
#160000
0"
0$
#165000
b0 &
b0 !
1"
1$
#170000
0"
0$
#175000
b1 &
b1 !
1"
1$
#180000
0"
0$
#185000
b10 &
b10 !
1"
1$
#190000
0"
0$
#195000
b11 &
b11 !
1"
1$
#200000
0"
0$
#205000
b100 &
b100 !
1"
1$
