Sequential Circuits/Flip-Flop/D Flip-Flop/d_ff.v
module d_ff (
    input D,       // Data input
    input CLK,     // Clock input
    output reg Q,  // Output
    output Qbar    // Complement output
);

assign Qbar = ~Q;

always @(posedge CLK) begin
    Q <= D;       // Q follows D on rising clock edge
end

endmodule

Sequential Circuits/Flip-Flop/D Flip-Flop/d_ff_tb.v


module d_ff_tb;

reg D, CLK;
wire Q, Qbar;

// Instantiate the D Flip-Flop
d_ff uut (
    .D(D),
    .CLK(CLK),
    .Q(Q),
    .Qbar(Qbar)
);

// Clock generation (10ns period)
initial CLK = 0;
always #5 CLK = ~CLK;

initial begin
    // Create waveform file
    $dumpfile("d_ff_out.vcd");
    $dumpvars(0, d_ff_tb);

    // Initialize inputs
    D = 0;

    // Test sequence
    #2  D = 0;
    #10 D = 1;
    #10 D = 0;
    #10 D = 1;
    #10 D = 1;
    #10 D = 0;
    #20 $finish;
end

initial begin
    $monitor("Time=%0t | CLK=%b | D=%b | Q=%b Qbar=%b", $time, CLK, D, Q, Qbar);
end

endmodule

Sequential Circuits/Flip-Flop/D Flip-Flop/d_ff_out.vcd
$date
	Thu Oct 02 22:56:50 2025
$end
$version
	Icarus Verilog
$end
$timescale
	1s
$end
$scope module d_ff_tb $end
$var wire 1 ! Q $end
$var wire 1 " Qbar $end
$var reg 1 # CLK $end
$var reg 1 $ D $end
$scope module uut $end
$var wire 1 % CLK $end
$var wire 1 & D $end
$var wire 1 " Qbar $end
$var reg 1 ' Q $end
$upscope $end
$upscope $end
$enddefinitions $end
#0
$dumpvars
x'
0&
0%
0$
0#
x"
x!
$end
#5
1"
0'
0!
1#
1%
#10
0#
0%
#12
1$
1&
#15
0"
1'
1!
1#
1%
#20
0#
0%
#22
0$
0&
#25
1"
0'
0!
1#
1%
#30
0#
0%
#32
1$
1&
#35
0"
1'
1!
1#
1%
#40
0#
0%
#45
1#
1%
#50
0#
0%
#52
0$
0&
#55
1"
0'
0!
1#
1%
