Combinational Circuits/Full Adder/full_adder_structural.v
module full_adder_structural(
    input A, B, Cin,
    output Sum, Carry
);

wire sum1, carry1, carry2;

// First Half Adder
xor (sum1, A, B);
and (carry1, A, B);

// Second Half Adder
xor (Sum, sum1, Cin);
and (carry2, sum1, Cin);

// Final Carry Output
or (Carry, carry1, carry2);

endmodule

Combinational Circuits/full_adder_tb.v
module full_adder_tb;
    reg A, B, Cin;
    wire Sum, Carry;

    // Instantiate the Full Adder Structural model
    full_adder_structural uut (
        .A(A), .B(B), .Cin(Cin),
        .Sum(Sum), .Carry(Carry)
    );

    initial begin
        $dumpfile("full_adder_structural.vcd");
        $dumpvars(0, full_adder_tb);

        $display("A B Cin | Sum Carry");
        $display("-------------------");

        A=0; B=0; Cin=0; #10;
        $display("%b %b  %b  |  %b    %b", A, B, Cin, Sum, Carry);

        A=0; B=0; Cin=1; #10;
        $display("%b %b  %b  |  %b    %b", A, B, Cin, Sum, Carry);

        A=0; B=1; Cin=0; #10;
        $display("%b %b  %b  |  %b    %b", A, B, Cin, Sum, Carry);

        A=0; B=1; Cin=1; #10;
        $display("%b %b  %b  |  %b    %b", A, B, Cin, Sum, Carry);

        A=1; B=0; Cin=0; #10;
        $display("%b %b  %b  |  %b    %b", A, B, Cin, Sum, Carry);

        A=1; B=0; Cin=1; #10;
        $display("%b %b  %b  |  %b    %b", A, B, Cin, Sum, Carry);

        A=1; B=1; Cin=0; #10;
        $display("%b %b  %b  |  %b    %b", A, B, Cin, Sum, Carry);

        A=1; B=1; Cin=1; #10;
        $display("%b %b  %b  |  %b    %b", A, B, Cin, Sum, Carry);

        $finish;
    end
endmodule

Combinational Circuits/Full Adder/full_adder_structural.vcd
$date
	Wed Jul 16 00:22:17 2025
$end
$version
	Icarus Verilog
$end
$timescale
	1s
$end
$scope module full_adder_tb $end
$var wire 1 ! Carry $end
$var wire 1 " Sum $end
$var reg 1 # A $end
$var reg 1 $ B $end
$var reg 1 % Cin $end
$scope module uut $end
$var wire 1 & A $end
$var wire 1 ' B $end
$var wire 1 ! Carry $end
$var wire 1 ( Cin $end
$var wire 1 " Sum $end
$var wire 1 ) carry1 $end
$var wire 1 * carry2 $end
$var wire 1 + sum1 $end
$upscope $end
$upscope $end
$enddefinitions $end
#0
$dumpvars
0+
0*
0)
0(
0'
0&
0%
0$
0#
0"
0!
$end
#10
1"
1%
1(
#20
1+
0%
0(
1$
1'
#30
1!
0"
1*
1%
1(
#40
0!
1"
0*
0%
0(
0$
0'
1#
1&
#50
1!
0"
1*
1%
1(
#60
0*
0+
1)
0%
0(
1$
1'
#70
1"
1%
1(
