Sequential Circuits/Counters/Asynchronous Counters/rc_up_counter.v
module rc_up_counter (
    input clk, reset,
    output [3:0] q
);

    wire q0, q1, q2, q3;

    // First T flip-flop toggles on main clock
    t_ff ff0 (.clk(clk),     .reset(reset), .T(1'b1), .q(q0));
    // Subsequent TFFs toggle on negedge of previous Q
    t_ff ff1 (.clk(~q0),    .reset(reset), .T(1'b1), .q(q1));
    t_ff ff2 (.clk(~q1),    .reset(reset), .T(1'b1), .q(q2));
    t_ff ff3 (.clk(~q2),    .reset(reset), .T(1'b1), .q(q3));

    
    assign q = {q3, q2, q1, q0};

endmodule

// T Flip-Flop Module
module t_ff (
    input clk, reset, T,
    output reg q
);
    always @(posedge clk or posedge reset) begin
        if (reset)
            q <= 1'b0;
        else if (T)
            q <= ~q;
    end
endmodule

Sequential Circuits/Counters/Asynchronous Counters/rc_up_counter_tb.v

module rc_up_counter_tb;

    reg clk, reset;
    wire [3:0] q;

    // Instantiate the counter
    rc_up_counter uut (
        .clk(clk),
        .reset(reset),
        .q(q)
    );

    // Clock generation: 10ns period
    always #5 clk = ~clk;

    initial begin
        // VCD dump for waveform viewing
        $dumpfile("rc_up_counter_out.vcd");
        $dumpvars(0, rc_up_counter_tb);

        // Initialize
        clk = 0;
        reset = 1;

        // Release reset after some time
        #10 reset = 0;

        // Run simulation for some time
        #200 $finish;
    end

endmodule

Sequential Circuits/Counters/Asynchronous Counters/rc_up_counter_out.vcd
$date
	Fri Oct 03 10:46:15 2025
$end
$version
	Icarus Verilog
$end
$timescale
	1s
$end
$scope module rc_up_counter_tb $end
$var wire 4 ! q [3:0] $end
$var reg 1 " clk $end
$var reg 1 # reset $end
$scope module uut $end
$var wire 1 $ clk $end
$var wire 4 % q [3:0] $end
$var wire 1 & q0 $end
$var wire 1 ' q1 $end
$var wire 1 ( q2 $end
$var wire 1 ) q3 $end
$var wire 1 * reset $end
$scope module ff0 $end
$var wire 1 + T $end
$var wire 1 $ clk $end
$var wire 1 * reset $end
$var reg 1 , q $end
$upscope $end
$scope module ff1 $end
$var wire 1 - T $end
$var wire 1 . clk $end
$var wire 1 * reset $end
$var reg 1 / q $end
$upscope $end
$scope module ff2 $end
$var wire 1 0 T $end
$var wire 1 1 clk $end
$var wire 1 * reset $end
$var reg 1 2 q $end
$upscope $end
$scope module ff3 $end
$var wire 1 3 T $end
$var wire 1 4 clk $end
$var wire 1 * reset $end
$var reg 1 5 q $end
$upscope $end
$upscope $end
$upscope $end
$enddefinitions $end
#0
$dumpvars
05
14
13
02
11
10
0/
1.
1-
0,
1+
1*
0)
0(
0'
0&
b0 %
0$
1#
0"
b0 !
$end
#5
1"
1$
#10
0"
0$
0#
0*
#15
0.
1,
b1 !
b1 %
1&
1"
1$
#20
0"
0$
#25
01
1/
1'
1.
0,
b10 !
b10 %
0&
1"
1$
#30
0"
0$
#35
0.
1,
b11 !
b11 %
1&
1"
1$
#40
0"
0$
#45
04
12
1(
11
0/
0'
1.
0,
b100 !
b100 %
0&
1"
1$
#50
0"
0$
#55
0.
1,
b101 !
b101 %
1&
1"
1$
#60
0"
0$
#65
01
1/
1'
1.
0,
b110 !
b110 %
0&
1"
1$
#70
0"
0$
#75
0.
1,
b111 !
b111 %
1&
1"
1$
#80
0"
0$
#85
15
1)
14
02
0(
11
0/
0'
1.
0,
b1000 !
b1000 %
0&
1"
1$
#90
0"
0$
#95
0.
1,
b1001 !
b1001 %
1&
1"
1$
#100
0"
0$
#105
01
1/
1'
1.
0,
b1010 !
b1010 %
0&
1"
1$
#110
0"
0$
#115
0.
1,
b1011 !
b1011 %
1&
1"
1$
#120
0"
0$
#125
04
12
1(
11
0/
0'
1.
0,
b1100 !
b1100 %
0&
1"
1$
#130
0"
0$
#135
0.
1,
b1101 !
b1101 %
1&
1"
1$
#140
0"
0$
#145
01
1/
1'
1.
0,
b1110 !
b1110 %
0&
1"
1$
#150
0"
0$
#155
0.
1,
b1111 !
b1111 %
1&
1"
1$
#160
0"
0$
#165
05
0)
14
02
0(
11
0/
0'
1.
0,
b0 !
b0 %
0&
1"
1$
#170
0"
0$
#175
0.
1,
b1 !
b1 %
1&
1"
1$
#180
0"
0$
#185
01
1/
1'
1.
0,
b10 !
b10 %
0&
1"
1$
#190
0"
0$
#195
0.
1,
b11 !
b11 %
1&
1"
1$
#200
0"
0$
#205
04
12
1(
11
0/
0'
1.
0,
b100 !
b100 %
0&
1"
1$
