Sequential Circuits/Flip-Flop/SR Flip Flop/sr_ff.v
module sr_ff (
    input S,       // Set
    input R,       // Reset
    input CLK,     // Clock
    output reg Q,  // Output
    output Qbar    // Complement output
);

assign Qbar = ~Q; 

always @(posedge CLK) begin
    case ({S,R})
        2'b00: Q <= Q;      // Hold
        2'b01: Q <= 0;      // Reset
        2'b10: Q <= 1;      // Set
        2'b11: Q <= 1'b x ;   // Invalid state
        default: Q <=1'b x;   // Default Value
    endcase
end

endmodule

Sequential Circuits/Flip-Flop/SR Flip Flop/sr_ff_tb.v

module sr_ff_tb;

reg S, R, CLK;
wire Q, Qbar;

// Instantiate the SR Flip-Flop
sr_ff uut (
    .S(S),
    .R(R),
    .CLK(CLK),
    .Q(Q),
    .Qbar(Qbar)
);

// Clock generation: 10ns period
initial CLK = 0;
always #5 CLK = ~CLK;  // toggles every 5ns

initial begin
    $dumpfile("sr_ff_out.vcd");
    $dumpvars(0, sr_ff_tb);

    // Initialize inputs
    S = 0; R = 0;

    // Test sequence
    #2 S=1; R=0;       // Set on next clock
    #10 S=0; R=0;      // Hold
    #10 S=0; R=1;      // Reset
    #10 S=0; R=0;      // Hold
    #10 S=1; R=1;      // Invalid state
    #10 S=0; R=0;      // Hold
    #20 $finish;
end

initial begin
    $monitor("Time=%0t | CLK=%b | S=%b R=%b | Q=%b Qbar=%b", 
             $time, CLK, S, R, Q, Qbar);
   end

endmodule

Sequential Circuits/Flip-Flop/SR Flip Flop/sr_ff_out.vcd
$date
	Thu Oct 02 21:34:35 2025
$end
$version
	Icarus Verilog
$end
$timescale
	1s
$end
$scope module sr_ff_tb $end
$var wire 1 ! Q $end
$var wire 1 " Qbar $end
$var reg 1 # CLK $end
$var reg 1 $ R $end
$var reg 1 % S $end
$scope module uut $end
$var wire 1 & CLK $end
$var wire 1 " Qbar $end
$var wire 1 ' R $end
$var wire 1 ( S $end
$var reg 1 ) Q $end
$upscope $end
$upscope $end
$enddefinitions $end
#0
$dumpvars
x)
0(
0'
0&
0%
0$
0#
x"
x!
$end
#2
1%
1(
#5
0"
1)
1!
1#
1&
#10
0#
0&
#12
0%
0(
#15
1#
1&
#20
0#
0&
#22
1$
1'
#25
1"
0)
0!
1#
1&
#30
0#
0&
#32
0$
0'
#35
1#
1&
#40
0#
0&
#42
1$
1'
1%
1(
#45
x"
x)
x!
1#
1&
#50
0#
0&
#52
0$
0'
0%
0(
