Sequential Circuits/Flip-Flop/T Flip-Flop/t_ff.v
module t_ff (
    input T, CLK,
    output reg Q,
    output Qbar
);

assign Qbar = ~Q;

initial Q=0;

always @(posedge CLK) begin
    case (T)
        1'b0: Q <= Q;       // Hold state
        1'b1: Q <= ~Q;      // Toggle state
        default: Q <= Q;    // Safe default
    endcase
end

endmodule

Sequential Circuits/Flip-Flop/T Flip-Flop/t_ff_tb.v

module t_ff_tb;

reg T, CLK;
wire Q, Qbar;

// Instantiate T Flip-Flop
t_ff uut (
    .T(T),
    .CLK(CLK),
    .Q(Q),
    .Qbar(Qbar)
);

// Clock generation (10ns period)
initial CLK = 0;
always #5 CLK = ~CLK;

initial begin
    $dumpfile("t_ff_out.vcd");
    $dumpvars(0, t_ff_tb);

    // Initialize
    T = 0;

    // Test sequence
    #10 T = 0;   // Hold
    #10 T = 1;   // Toggle
    #10 T = 1;   // Toggle again
    #10 T = 0;   // Hold
    #10 T = 1;   // Toggle
    #20 $finish;
end

initial begin
    $monitor("Time=%0t | CLK=%b | T=%b | Q=%b | Qbar=%b",
              $time, CLK, T, Q, Qbar);
end

endmodule

Sequential Circuits/Flip-Flop/T Flip-Flop/t_ff_out.vcd
$date
	Fri Oct 03 00:34:45 2025
$end
$version
	Icarus Verilog
$end
$timescale
	1s
$end
$scope module t_ff_tb $end
$var wire 1 ! Q $end
$var wire 1 " Qbar $end
$var reg 1 # CLK $end
$var reg 1 $ T $end
$scope module uut $end
$var wire 1 % CLK $end
$var wire 1 " Qbar $end
$var wire 1 & T $end
$var reg 1 ' Q $end
$upscope $end
$upscope $end
$enddefinitions $end
#0
$dumpvars
0'
0&
0%
0$
0#
1"
0!
$end
#5
1#
1%
#10
0#
0%
#15
1#
1%
#20
0#
0%
1$
1&
#25
0"
1'
1!
1#
1%
#30
0#
0%
#35
1"
0'
0!
1#
1%
#40
0#
0%
0$
0&
#45
1#
1%
#50
0#
0%
1$
1&
#55
0"
1'
1!
1#
1%
#60
0#
0%
#65
1"
0'
0!
1#
1%
